jupyterlab_telemetry_system/__init__.py
jupyterlab_telemetry_system/_version.py
jupyterlab_telemetry_system/application.py
jupyterlab_telemetry_system/handlers.py
jupyterlab_telemetry_system-0.1.1.data/data/etc/jupyter/jupyter_server_config.d/jupyterlab_telemetry_system.json
jupyterlab_telemetry_system-0.1.1.data/data/share/jupyter/labextensions/jupyterlab-telemetry-system/package.json
jupyterlab_telemetry_system-0.1.1.data/data/share/jupyter/labextensions/jupyterlab-telemetry-system/static/747.42d9e7ae21237560d1a3.js
jupyterlab_telemetry_system-0.1.1.data/data/share/jupyter/labextensions/jupyterlab-telemetry-system/static/798.9c7511dd417459ff1820.js
jupyterlab_telemetry_system-0.1.1.data/data/share/jupyter/labextensions/jupyterlab-telemetry-system/static/remoteEntry.762f82242e5971bd7f66.js
jupyterlab_telemetry_system-0.1.1.data/data/share/jupyter/labextensions/jupyterlab-telemetry-system/static/style.js
jupyterlab_telemetry_system-0.1.1.data/data/share/jupyter/labextensions/jupyterlab-telemetry-system/static/third-party-licenses.json
jupyterlab_telemetry_system-0.1.1.data/data/share/jupyter/labextensions/jupyterlab-telemetry-system/install.json
jupyterlab_telemetry_system-0.1.1.dist-info/METADATA
jupyterlab_telemetry_system-0.1.1.dist-info/WHEEL
jupyterlab_telemetry_system-0.1.1.dist-info/licenses/LICENSE
jupyterlab_telemetry_system-0.1.1.dist-info/RECORD
